datasetplus/__init__.py
datasetplus/core.py
datasetplus-0.6.0.dist-info/METADATA
datasetplus-0.6.0.dist-info/WHEEL
datasetplus-0.6.0.dist-info/top_level.txt
datasetplus-0.6.0.dist-info/RECORD
