Metadata-Version: 2.4
Name: datasetplus
Version: 0.6.0
Summary: An enhanced wrapper for Hugging Face datasets with additional functionality
Author-email: sweeneyhe <sweeenyhe@gmail.com>
Project-URL: Homepage, https://github.com/SWEENEYHE/DatasetPlus
Project-URL: Bug Reports, https://github.com/SWEENEYHE/DatasetPlus/issues
Project-URL: Source, https://github.com/SWEENEYHE/DatasetPlus
Keywords: datasets,data processing,nlp
Classifier: Development Status :: 3 - Alpha
Classifier: Intended Audience :: Developers
Classifier: Intended Audience :: Science/Research
Classifier: License :: OSI Approved :: MIT License
Classifier: Operating System :: OS Independent
Classifier: Programming Language :: Python :: 3
Classifier: Programming Language :: Python :: 3.7
Classifier: Programming Language :: Python :: 3.8
Classifier: Programming Language :: Python :: 3.9
Classifier: Programming Language :: Python :: 3.10
Classifier: Programming Language :: Python :: 3.11
Classifier: Topic :: Scientific/Engineering :: Artificial Intelligence
Classifier: Topic :: Software Development :: Libraries :: Python Modules
Requires-Python: >=3.7
Requires-Dist: datasets>=2.0.0
Requires-Dist: pandas>=1.3.0
Requires-Dist: numpy>=1.21.0
Requires-Dist: openpyxl>=3.0.0
Requires-Dist: xlrd>=2.0.0
Requires-Dist: pyarrow>=5.0.0
Requires-Dist: tqdm>=4.62.0
Requires-Dist: requests>=2.25.0
